.bzrignore
COPYING
README.txt
bzrsync.wpr
bzrsync.wpu
bzrsync.yaml
setup.py
bzrsync/__init__.py
bzrsync/cmd.py
bzrsync/setup_info.py
bzrsync/wsgiserver.py
bzrsync.egg-info/PKG-INFO
bzrsync.egg-info/SOURCES.txt
bzrsync.egg-info/dependency_links.txt
bzrsync.egg-info/entry_points.txt
bzrsync.egg-info/requires.txt
bzrsync.egg-info/top_level.txt
bzrsync.egg-info/zip-safe
dev-docs/CherryPyTutorial.html
dev-docs/PyjamasWithCherryPyJSONRPC.html
dev-docs/python-json-rpc.html
dev-docs/super-simple-rpc-in-cherrypy.html
dev-docs/CherryPyTutorial_files/cplogo.jpg
dev-docs/CherryPyTutorial_files/trac.css
dev-docs/CherryPyTutorial_files/trac.js
dev-docs/CherryPyTutorial_files/trac_logo_mini.png
dev-docs/CherryPyTutorial_files/webfaction.gif
dev-docs/CherryPyTutorial_files/wiki.css
dev-docs/PyjamasWithCherryPyJSONRPC_files/codesite_product_dictionary_ph.js
dev-docs/PyjamasWithCherryPyJSONRPC_files/core_scripts_20081103.js
dev-docs/PyjamasWithCherryPyJSONRPC_files/dit_scripts.js
dev-docs/PyjamasWithCherryPyJSONRPC_files/ga.js
dev-docs/PyjamasWithCherryPyJSONRPC_files/logo.png
dev-docs/PyjamasWithCherryPyJSONRPC_files/ph_core.css
dev-docs/PyjamasWithCherryPyJSONRPC_files/ph_detail.css
dev-docs/PyjamasWithCherryPyJSONRPC_files/prettify.js
dev-docs/PyjamasWithCherryPyJSONRPC_files/star_off.gif
dev-docs/PyjamasWithCherryPyJSONRPC_files/tearoff_icon.gif
dev-docs/python-json-rpc_files/jquery.js
dev-docs/python-json-rpc_files/search.js
dev-docs/python-json-rpc_files/trac.css
dev-docs/python-json-rpc_files/trac.js
dev-docs/python-json-rpc_files/trac_logo_mini.png
dev-docs/python-json-rpc_files/wiki.css
dev-docs/super-simple-rpc-in-cherrypy_files/badge_code.html
dev-docs/super-simple-rpc-in-cherrypy_files/main.css
dev-docs/super-simple-rpc-in-cherrypy_files/rediscover.gif