Metadata-Version: 1.0
Name: bzrsync
Version: 0.2
Summary: Tool to automatically synchronize Bazaar repositories between multiple nodes
Home-page: http://pypi.python.org/pypi/bzrsync/
Author: Marco Pantaleoni
Author-email: m.pantaleoni@softwarefabrica.org
License: GNU GPL v2
Keywords: softwarefabrica bazaar bzr sync bzrsync synchronize synchronization repositories branches vcs version control
Platform: UNKNOWN
Classifier: Topic :: Software Development :: Version Control
Classifier: Topic :: Software Development
Classifier: Topic :: Utilities
Classifier: Intended Audience :: Developers
Classifier: Intended Audience :: System Administrators
Classifier: Intended Audience :: End Users/Desktop
Classifier: License :: OSI Approved :: GNU General Public License (GPL)
Classifier: Operating System :: OS Independent
Classifier: Development Status :: 4 - Beta
Classifier: Programming Language :: Python :: 2.6
Classifier: Environment :: Console
